oss/remote/__init__.py
oss/remote/app.py
oss/remote/bin/__init__.py
oss/remote/bin/remote.py
oss/remote/models/__init__.py
oss/remote/remotes/__init__.py
oss/remote/remotes/buttonpad.py
oss/remote/remotes/keypad.py
oss/remote/remotes/type.py
openshootingsolutions_remote-0.0.5.dist-info/LICENSE
openshootingsolutions_remote-0.0.5.dist-info/METADATA
openshootingsolutions_remote-0.0.5.dist-info/WHEEL
openshootingsolutions_remote-0.0.5.dist-info/entry_points.txt
openshootingsolutions_remote-0.0.5.dist-info/RECORD
