Metadata-Version: 2.1
Name: openshootingsolutions-remote
Version: 0.0.5
Summary: OSS remote package
License: GPL-3.0-or-later
Author: Arnoud Stolk
Requires-Python: >=3.12,<4.0
Classifier: License :: OSI Approved :: GNU General Public License v3 or later (GPLv3+)
Classifier: Programming Language :: Python :: 3
Classifier: Programming Language :: Python :: 3.12
Classifier: Programming Language :: Python :: 3.13
Requires-Dist: keyboard (>=0.13.5,<0.14.0)
Requires-Dist: openshootingsolutions-core (>=0.0.1,<0.0.2)
Requires-Dist: pika (>=1.3.2,<2.0.0)
Requires-Dist: pydantic (>=2.9.2,<3.0.0)
